markov_word_generator.py
markov_word_generator-0.6.dist-info/LICENSE
markov_word_generator-0.6.dist-info/METADATA
markov_word_generator-0.6.dist-info/WHEEL
markov_word_generator-0.6.dist-info/top_level.txt
markov_word_generator-0.6.dist-info/RECORD
